SFRScalculator/__init__.py
SFRScalculator/sfr_calculator.py
SFRscalculator-0.0.1.dist-info/METADATA
SFRscalculator-0.0.1.dist-info/WHEEL
SFRscalculator-0.0.1.dist-info/top_level.txt
SFRscalculator-0.0.1.dist-info/RECORD
