Metadata-Version: 2.1
Name: SFRscalculator
Version: 0.0.1
Requires-Dist: numpy
Requires-Dist: scikit-learn
Requires-Dist: pandas
Requires-Dist: matplotlib
